django_layered_start/__init__.py
django_layered_start/cli.py
django_layered_start/core/__init__.py
django_layered_start/core/app_creator.py
django_layered_start/core/layered_structure.py
django_layered_start/core/project_creator.py
django_layered_start-1.2.2.dist-info/licenses/LICENSE
django_layered_start-1.2.2.dist-info/METADATA
django_layered_start-1.2.2.dist-info/WHEEL
django_layered_start-1.2.2.dist-info/entry_points.txt
django_layered_start-1.2.2.dist-info/top_level.txt
django_layered_start-1.2.2.dist-info/RECORD
